README.rst
setup.py
digital_root/__init__.py
digital_root/digital_root.py
digital_root.egg-info/PKG-INFO
digital_root.egg-info/SOURCES.txt
digital_root.egg-info/dependency_links.txt
digital_root.egg-info/entry_points.txt
digital_root.egg-info/top_level.txt