Metadata-Version: 2.1
Name: digital-root
Version: 0.3
Summary: Script for calculating digital root of an integer number.
Home-page: https://github.com/urosjevremovic/digital-root
Author: Uros Jevremovic
Author-email: jevremovic.uros91@gmail.com
License: MIT
Platform: UNKNOWN
